{
    "type": "wbButtonGroup",
    "fields": {
        "wbTitle": "Filter by Course",
        "wbButtonGroupType": "outline-primary",
        "wbButtonSize": "",
        "wbButtonGroupOrientation": "horizontal"
    },
    "items": [
        { "wbButtonLabel": "Starters",  "wbButtonUrl": "", "wbButtonTarget": "" },
        { "wbButtonLabel": "Mains",     "wbButtonUrl": "", "wbButtonTarget": "" },
        { "wbButtonLabel": "Desserts",  "wbButtonUrl": "", "wbButtonTarget": "" },
        { "wbButtonLabel": "Drinks",    "wbButtonUrl": "", "wbButtonTarget": "" }
    ]
}
